setup.py
distributions/Binomialdistribution.py
distributions/Gaussiandistribution.py
distributions/Generaldistribution.py
distributions/__init__.py
vistributions.egg-info/PKG-INFO
vistributions.egg-info/SOURCES.txt
vistributions.egg-info/dependency_links.txt
vistributions.egg-info/not-zip-safe
vistributions.egg-info/top_level.txt